upd_agent_skill/__init__.py
upd_agent_skill-0.1.1.dist-info/METADATA
upd_agent_skill-0.1.1.dist-info/WHEEL
upd_agent_skill-0.1.1.dist-info/RECORD
