Metadata-Version: 2.4
Name: upd-agent-skill
Version: 0.1.1
Summary: CLI tool for updating Claude Code, Codex, OpenCode, Amp, Clawdbot agent skills.
Project-URL: Repository, https://upd.dev/skills/agent-skills-project
License-Expression: MIT
Keywords: agent,ai,claude,claude-code,clawdbot,clawdhub,codex,open-code,skill
Requires-Python: >=3.10
